countdownfmt/__init__.py
countdownfmt/_countdown.py
countdownfmt/constants.py
countdownfmt/types.py
countdownfmt-0.0.1.dist-info/LICENSE
countdownfmt-0.0.1.dist-info/METADATA
countdownfmt-0.0.1.dist-info/WHEEL
countdownfmt-0.0.1.dist-info/top_level.txt
countdownfmt-0.0.1.dist-info/RECORD
