Metadata-Version: 2.1
Name: countdownfmt
Version: 0.0.1
Summary: An easy-to-use and highly customizable formatter used to turn a time value into a countdown string
Author-email: "Tanner B. Corcoran" <tannerbcorcoran@gmail.com>
Project-URL: Homepage, https://github.com/tanrbobanr/countdownfmt
Classifier: Programming Language :: Python :: 3
Classifier: License :: OSI Approved :: MIT License
Classifier: Operating System :: OS Independent
Requires-Python: >=3.9
License-File: LICENSE
Requires-Dist: plogging (>=0.0.1)
